aerosense_tools/__init__.py
aerosense_tools-0.1.0.dist-info/LICENSE
aerosense_tools-0.1.0.dist-info/WHEEL
aerosense_tools-0.1.0.dist-info/METADATA
aerosense_tools-0.1.0.dist-info/RECORD
