Metadata-Version: 2.1
Name: aerosense-tools
Version: 0.1.0
Summary: Functions for working with aerosense data, useful in building dashboards, analysis notebooks and digital twin services
Home-page: https://github.com/aerosense-ai/aerosense-tools
License: BSD-3
Keywords: aerosense,tools
Author: Tom Clark
Requires-Python: >=3.8,<3.11
Classifier: Development Status :: 4 - Beta
Classifier: Intended Audience :: Developers
Classifier: License :: OSI Approved :: BSD License
Classifier: License :: Other/Proprietary License
Classifier: Operating System :: OS Independent
Classifier: Programming Language :: Python :: 3
Classifier: Programming Language :: Python :: 3.10
Classifier: Programming Language :: Python :: 3.8
Classifier: Programming Language :: Python :: 3.9
Classifier: Topic :: Software Development :: Libraries :: Python Modules
Project-URL: Repository, https://github.com/aerosense-ai/aerosense-tools
